garmin_to_fittrackee/fittrackee.py
garmin_to_fittrackee/logs.py
garmin_to_fittrackee/main.py
garmin_to_fittrackee/sports.py
garmin_to_fittrackee/workout.py
garmin_to_fittrackee-0.11.1.dist-info/METADATA
garmin_to_fittrackee-0.11.1.dist-info/WHEEL
garmin_to_fittrackee-0.11.1.dist-info/entry_points.txt
garmin_to_fittrackee-0.11.1.dist-info/licenses/LICENSE
garmin_to_fittrackee-0.11.1.dist-info/RECORD
