Metadata-Version: 2.4
Name: garmin-to-fittrackee
Version: 0.11.1
Summary: A simple script to synchronize garmin to fittrackee. Inspired by https://github.com/jat255/strava-to-fittrackee
License: GPL-3
License-File: LICENSE
Author: Dryusdan
Author-email: contact@dryusdan.fr
Requires-Python: >=3.10,<4.0
Classifier: License :: Other/Proprietary License
Classifier: Programming Language :: Python :: 3
Classifier: Programming Language :: Python :: 3.10
Classifier: Programming Language :: Python :: 3.11
Classifier: Programming Language :: Python :: 3.12
Classifier: Programming Language :: Python :: 3.13
Classifier: Programming Language :: Python :: 3.14
Requires-Dist: garminconnect (>=0.2.26,<0.3.0)
Requires-Dist: packaging (>=25.0,<26.0)
Requires-Dist: pendulum (>=3.1.0,<4.0.0)
Requires-Dist: pyyaml (>=6.0.2,<7.0.0)
Requires-Dist: requests (>=2.32.3,<3.0.0)
Requires-Dist: requests-oauthlib (>=2.0.0,<3.0.0)
Requires-Dist: typer (>=0.16.0,<0.17.0)
